flowlogs_reader/__init__.py
flowlogs_reader/__main__.py
flowlogs_reader/aggregation.py
flowlogs_reader/flowlogs_reader.py
flowlogs_reader-5.0.1.dist-info/LICENSE
flowlogs_reader-5.0.1.dist-info/METADATA
flowlogs_reader-5.0.1.dist-info/WHEEL
flowlogs_reader-5.0.1.dist-info/entry_points.txt
flowlogs_reader-5.0.1.dist-info/top_level.txt
flowlogs_reader-5.0.1.dist-info/RECORD
