Metadata-Version: 2.1
Name: flowlogs-reader
Version: 5.0.1
Summary: Reader for AWS VPC Flow Logs
Home-page: https://github.com/obsrvbl-oss/flowlogs-reader
Author: Observable Networks
Author-email: support@observable.net
License: Apache
Classifier: Intended Audience :: Developers
Classifier: Intended Audience :: Information Technology
Classifier: Intended Audience :: System Administrators
Classifier: License :: OSI Approved :: Apache Software License
Classifier: Programming Language :: Python :: 3
Requires-Python: >=3.6
License-File: LICENSE
Requires-Dist: boto3 >=1.14.0
Requires-Dist: botocore >=1.17.0
Requires-Dist: parquet >=1.3.1
Requires-Dist: python-dateutil >=2.7.0
